rev_reader/__init__.py
rev_reader/rev_reader.py
rev_reader-0.0.3.dist-info/LICENSE
rev_reader-0.0.3.dist-info/METADATA
rev_reader-0.0.3.dist-info/WHEEL
rev_reader-0.0.3.dist-info/top_level.txt
rev_reader-0.0.3.dist-info/RECORD
