Metadata-Version: 2.1
Name: rev-reader
Version: 0.0.3
Summary: Convert transcriptions from rev into FAVE format.
Home-page: https://github.com/patrickschu/rev-reader
Author: Patrick
Author-email: patrickschultz@utexas.edu
License: MIT
Platform: UNKNOWN
Classifier: License :: OSI Approved :: MIT License
Classifier: Programming Language :: Python
Classifier: Programming Language :: Python :: Implementation :: CPython
Classifier: Programming Language :: Python :: Implementation :: PyPy
Requires-Python: >=2.7.11
Requires-Dist: pandas (>=0.22.1)
